lambda_pyathena-1.9.0.data/data/LICENSE
lambda_pyathena-1.9.0.data/data/Pipfile
lambda_pyathena-1.9.0.data/data/Pipfile.lock
lambda_pyathena-1.9.0.data/data/README.rst
pyathena/__init__.py
pyathena/async_cursor.py
pyathena/async_pandas_cursor.py
pyathena/common.py
pyathena/connection.py
pyathena/converter.py
pyathena/cursor.py
pyathena/error.py
pyathena/formatter.py
pyathena/model.py
pyathena/pandas_cursor.py
pyathena/result_set.py
pyathena/sqlalchemy_athena.py
pyathena/util.py
lambda_pyathena-1.9.0.dist-info/LICENSE
lambda_pyathena-1.9.0.dist-info/METADATA
lambda_pyathena-1.9.0.dist-info/WHEEL
lambda_pyathena-1.9.0.dist-info/entry_points.txt
lambda_pyathena-1.9.0.dist-info/top_level.txt
lambda_pyathena-1.9.0.dist-info/RECORD
