Metadata-Version: 2.1
Name: lambda-pyathena
Version: 1.9.0
Summary: Python DB API 2.0 (PEP 249) compliant client for Amazon Athena
Home-page: https://github.com/laughingman7743/PyAthena/
Author: laughingman7743
Author-email: laughingman7743@gmail.com
License: MIT License
Platform: UNKNOWN
Classifier: Development Status :: 4 - Beta
Classifier: Intended Audience :: Developers
Classifier: License :: OSI Approved :: MIT License
Classifier: Operating System :: OS Independent
Classifier: Topic :: Database :: Front-Ends
Classifier: Programming Language :: Python :: 2
Classifier: Programming Language :: Python :: 2.7
Classifier: Programming Language :: Python :: 3
Classifier: Programming Language :: Python :: 3.5
Classifier: Programming Language :: Python :: 3.6
Classifier: Programming Language :: Python :: 3.7
Requires-Dist: future
Requires-Dist: tenacity (>=4.1.0)
Requires-Dist: futures ; python_version == "2.7"
Provides-Extra: pandas
Requires-Dist: pandas (>=0.24.0) ; extra == 'pandas'
Provides-Extra: sqlalchemy
Requires-Dist: SQLAlchemy (<2.0.0,>=1.0.0) ; extra == 'sqlalchemy'
